lch_etl/__init__.py
lch_etl/bigdata.py
lch_etl/db4.py
lch_etl/dbv2.py
lch_etl/tool.py
lch_etl-1.0.2.dist-info/METADATA
lch_etl-1.0.2.dist-info/WHEEL
lch_etl-1.0.2.dist-info/top_level.txt
lch_etl-1.0.2.dist-info/RECORD
